numeros_primos/__init__.py
numeros_primos-1.0.dist-info/LICENSE
numeros_primos-1.0.dist-info/METADATA
numeros_primos-1.0.dist-info/WHEEL
numeros_primos-1.0.dist-info/top_level.txt
numeros_primos-1.0.dist-info/RECORD
