Metadata-Version: 2.1
Name: numeros-primos
Version: 1.0
Summary: calculo de numeros primos usando R
Home-page: UNKNOWN
Author: Ignacio Garcia
Author-email: author@example.com
License: GNU GPLv3
Platform: UNKNOWN
Classifier: Programming Language :: Python :: 3
Classifier: License :: OSI Approved :: MIT License
Classifier: Operating System :: OS Independent
